atalert/__init__.py
atalert/atalert.py
atalert/integrations.py
atalert/shipyard.py
atalert/zapier.py
atalert-0.1.10.dist-info/LICENSE
atalert-0.1.10.dist-info/WHEEL
atalert-0.1.10.dist-info/METADATA
atalert-0.1.10.dist-info/RECORD
