Metadata-Version: 2.1
Name: atalert
Version: 0.1.10
Summary: Atalert slack alerting service helper module
Home-page: https://atalert.dev
License: MIT
Keywords: alert,slack webhook,data pipeline,data engineering,data pipeline monitoring
Author: Kevin Haggerty
Author-email: kevin@splatcollision.com
Requires-Python: >=3.7,<4.0
Classifier: Intended Audience :: Developers
Classifier: Intended Audience :: Science/Research
Classifier: Intended Audience :: System Administrators
Classifier: License :: OSI Approved :: MIT License
Classifier: Programming Language :: Python :: 3
Classifier: Programming Language :: Python :: 3 :: Only
Classifier: Programming Language :: Python :: 3.10
Classifier: Programming Language :: Python :: 3.7
Classifier: Programming Language :: Python :: 3.8
Classifier: Programming Language :: Python :: 3.9
Classifier: Topic :: Database
Classifier: Topic :: Database :: Front-Ends
Classifier: Topic :: System :: Logging
Classifier: Topic :: System :: Monitoring
Requires-Dist: requests (>=2.22,<3.0)
Project-URL: Repository, https://github.com/atalert-dev/atalert-python
